menuware
menuware/templatetags
menuware/tests
